{"Exif":{"Lat":30.263102777777778,"Long":120.15833055555557,"Date":"2021-12-25T17:19:38+08:00","Tags":{"ApertureValue":1.58,"BrightnessValue":2.39,"ComponentsConfiguration":"","CustomRendered|int":"1","DateTimeDigitized|time.Time":"2021-12-25T17:19:38+08:00","DateTimeOriginal|time.Time":"2021-12-25T17:19:38+08:00","DateTime|time.Time":"2021-12-25T17:19:38+08:00","DigitalZoomRatio":0,"ExposureTime":0.029187,"FNumber":1.73,"FocalLength":4.38,"FocalLengthIn35mmFilm|int":"27","ISOSpeedRatings|int":"61","ImageLength|int":"4032","ImageWidth|int":"3024","InteroperabilityIFDPointer|int":"934","InteroperabilityIndex":"R98","LensMake":"Google","LensModel":"Pixel 4 back camera 4.38mm f/1.73","Make":"Google","MaxApertureValue":1.58,"Model":"Pixel 4","Orientation|int":"1","PixelXDimension|int":"3024","PixelYDimension|int":"4032","SceneCaptureType|int":"0","SceneType":"","ShutterSpeedValue":5.1,"Software":"HDR+ 1.0.414775603zd","SubSecTime":"541","SubSecTimeDigitized":"541","SubSecTimeOriginal":"541","SubjectDistance":10.186,"SubjectDistanceRange|int":"3","YCbCrPositioning|int":"1"}}}
